CommandRunner/__init__.py
SandboxCommandRunner-0.0.1.dist-info/METADATA
SandboxCommandRunner-0.0.1.dist-info/WHEEL
SandboxCommandRunner-0.0.1.dist-info/top_level.txt
SandboxCommandRunner-0.0.1.dist-info/RECORD
